setup.py
jquery_drop_widget/__init__.py
jquery_drop_widget/render.py
jquery_drop_widget.egg-info/PKG-INFO
jquery_drop_widget.egg-info/SOURCES.txt
jquery_drop_widget.egg-info/dependency_links.txt
jquery_drop_widget.egg-info/requires.txt
jquery_drop_widget.egg-info/top_level.txt