Metadata-Version: 1.0
Name: jquery-drop-widget
Version: 2010.10.14.0
Summary: Jquery based HTML Widget generation (compatible/made for dropSTAR webserver, but done generically.
Home-page: http://ge01f.com/demo/monitor/
Author: Geoff Howland
Author-email: geoff@gmail.com
License: MIT
Keywords: jquery widget html javascript css generating
Platform: UNKNOWN
Classifier: Development Status :: 4 - Beta
Classifier: Environment :: Web Environment
Classifier: Intended Audience :: Developers
Classifier: Intended Audience :: Information Technology
Classifier: Intended Audience :: System Administrators
Classifier: License :: OSI Approved :: MIT License
Classifier: Natural Language :: English
Classifier: Operating System :: OS Independent
Classifier: Programming Language :: Python :: 2.6
Classifier: Topic :: Text Processing :: Markup :: HTML
Classifier: Topic :: Internet :: WWW/HTTP
Classifier: Programming Language :: JavaScript
Classifier: Topic :: Software Development :: Code Generators
